discord/ext/prometheus/__init__.py
discord/ext/prometheus/prometheus_cog.py
discord/ext/prometheus/prometheus_logging_handler.py
discord_ext_prometheus-0.2.1.dist-info/METADATA
discord_ext_prometheus-0.2.1.dist-info/WHEEL
discord_ext_prometheus-0.2.1.dist-info/licenses/LICENSE
discord_ext_prometheus-0.2.1.dist-info/RECORD
