Metadata-Version: 2.4
Name: discord-ext-prometheus
Version: 0.2.1
Summary: An extension for the discord.py library that enables Prometheus metrics
Project-URL: Source, https://github.com/Apollo-Roboto/discord.py-ext-prometheus
Author-email: Apollo-Roboto <Apollo_Roboto@outlook.com>
License-Expression: MIT
License-File: LICENSE
Keywords: Analytics,Bot,Discord,Extension,Metrics,Prometheus
Classifier: License :: OSI Approved :: MIT License
Classifier: Natural Language :: English
Classifier: Operating System :: OS Independent
Classifier: Programming Language :: Python :: 3
Classifier: Programming Language :: Python :: 3.8
Classifier: Programming Language :: Python :: 3.9
Classifier: Programming Language :: Python :: 3.10
Classifier: Programming Language :: Python :: 3.11
Classifier: Topic :: Software Development :: Libraries
Classifier: Topic :: Software Development :: Libraries :: Python Modules
Classifier: Topic :: Utilities
Requires-Python: >=3.8
Requires-Dist: discord-py<3,>=2.2.3
Requires-Dist: prometheus-client<1,>=0.16.0
Provides-Extra: dev
Requires-Dist: black; extra == 'dev'
Requires-Dist: pylint; extra == 'dev'
